AUTHORS.rst
CONTRIBUTING.rst
HISTORY.rst
LICENSE
MANIFEST.in
README.rst
setup.cfg
setup.py
docs/Makefile
docs/authors.rst
docs/conf.py
docs/contributing.rst
docs/history.rst
docs/index.rst
docs/installation.rst
docs/make.bat
docs/readme.rst
docs/usage.rst
filter_classified_reads/__init__.py
filter_classified_reads/cli.py
filter_classified_reads/const.py
filter_classified_reads/io.py
filter_classified_reads/target_classified_reads.py
filter_classified_reads/tax_node.py
filter_classified_reads/util.py
filter_classified_reads.egg-info/PKG-INFO
filter_classified_reads.egg-info/SOURCES.txt
filter_classified_reads.egg-info/dependency_links.txt
filter_classified_reads.egg-info/entry_points.txt
filter_classified_reads.egg-info/not-zip-safe
filter_classified_reads.egg-info/requires.txt
filter_classified_reads.egg-info/top_level.txt
tests/test_filter_classified_reads.py
tests/data/SRR8207674-centrifuge_kreport.tsv
tests/data/SRR8207674-centrifuge_results.tsv
tests/data/SRR8207674-kraken2_report.tsv
tests/data/SRR8207674-kraken2_results.tsv
tests/data/SRR8207674_1.viral_unclassified.seqtk_seed42_n10000.fastq.gz
tests/data/SRR8207674_2.viral_unclassified.seqtk_seed42_n10000.fastq.gz