Metadata-Version: 1.1
Name: filter-classified-reads
Version: 0.2.0
Summary: Filter for reads from taxa of interest using Kraken2/Centrifuge classification results
Home-page: https://github.com/peterk87/filter_classified_reads
Author: Peter Kruczkiewicz
Author-email: peter.kruczkiewicz@gmail.com
License: Apache Software License 2.0
Keywords: filter_classified_reads
Platform: UNKNOWN
Classifier: Development Status :: 2 - Pre-Alpha
Classifier: Intended Audience :: Developers
Classifier: License :: OSI Approved :: Apache Software License
Classifier: Natural Language :: English
Classifier: Programming Language :: Python :: 3
Classifier: Programming Language :: Python :: 3.6
Classifier: Programming Language :: Python :: 3.7
Classifier: Topic :: Scientific/Engineering
Classifier: Topic :: Scientific/Engineering :: Bio-Informatics
